massiprecon/__main__.py
massiprecon/massiprecon.py
massiprecon-0.0.14.dist-info/METADATA
massiprecon-0.0.14.dist-info/WHEEL
massiprecon-0.0.14.dist-info/top_level.txt
massiprecon-0.0.14.dist-info/RECORD
