Metadata-Version: 2.1
Name: massiprecon
Version: 0.0.14
Summary: Generate csv or jsons with ip info
Author: Witchdoctor (malectrica)
Keywords: python,hack,osint,recon,data,api,ip
Classifier: Development Status :: 5 - Production/Stable
Classifier: Intended Audience :: Developers
Classifier: Programming Language :: Python :: 3
Classifier: Operating System :: Unix
Classifier: Operating System :: MacOS :: MacOS X
Classifier: Operating System :: Microsoft :: Windows
Requires-Dist: argparse
Requires-Dist: advocate
